cortex2/__init__.py
cortex2/emotiv_cortex2_client.py
cortex2/emotiv_cortex2_client.py~Stashed changes
cortex2/lib/__init__.py
cortex2/lib/WebsocketClient/__init__.py
cortex2/lib/WebsocketClient/websocket_client.py
cortex2-1.0.1.dist-info/LICENSE
cortex2-1.0.1.dist-info/METADATA
cortex2-1.0.1.dist-info/WHEEL
cortex2-1.0.1.dist-info/top_level.txt
cortex2-1.0.1.dist-info/RECORD
