Metadata-Version: 2.1
Name: cortex2
Version: 1.0.1
Summary: Comprehensive threaded, asynchronous Python client for the Emotiv EEG Cortex 2 API
Home-page: https://github.com/methylDragon/emotiv-cortex2-python-client
Author: methylDragon
Author-email: methylDragon@gmail.com
License: MIT
Download-URL: https://pypi.org/project/cortex2/
Keywords: emotiv,eeg,client,websockets,api,bci,brain
Platform: UNKNOWN
Requires-Dist: websockets (>=7.0)
